{
    "namespace": "unreal",
    "unreal_type": "FSphere",
    "type": "class",
    "alias": "Sphere",
    "opaque_type": true,
    "properties": [],
    "apis": [
        {
            "name": "IsInside",
            "ret_type": "bool",
            "parameters": [
                {
                    "type": "&Sphere",
                    "name": "Other"
                },
                {
                    "type": "f32",
                    "name": "Tolerance"
                }
            ]
        }
    ]
}